gramps_web_api_client/.gitignore
gramps_web_api_client/__init__.py
gramps_web_api_client/_version.py
gramps_web_api_client/api.py
gramps_web_api_client-0.1.dist-info/METADATA
gramps_web_api_client-0.1.dist-info/WHEEL
gramps_web_api_client-0.1.dist-info/top_level.txt
gramps_web_api_client-0.1.dist-info/RECORD
