Metadata-Version: 2.1
Name: gramps-web-api-client
Version: 0.1
Summary: A simple Python client to interact with Gramps Web API
Author-email: "David M. Straub" <straub@protonmail.com>
License: MIT
Project-URL: homepage, https://github.com/DavidMStraub/gramps-web-api-client
Project-URL: repository, https://github.com/DavidMStraub/gramps-web-api-client
Requires-Dist: requests >=2.31.0
